tivol/__init__.py
tivol/admin.py
tivol/apps.py
tivol/models.py
tivol/views.py
tivol/base_classes/__init__.py
tivol/base_classes/assertions.py
tivol/base_classes/entry_point.py
tivol/base_classes/mappers.py
tivol/base_classes/migration_handler_base.py
tivol/base_classes/plugins.py
tivol/management/__init__.py
tivol/management/helpers.py
tivol/management/commands/__init__.py
tivol/management/commands/migrate_content.py
tivol/management/commands/migrations_info.py
tivol/management/commands/migrations_rollback.py
tivol/migrations/0001_initial.py
tivol/migrations/__init__.py
tivol/tests/__init__.py
tivol/tests/settings.py
tivol/tests/test_entrypoint.py
tivol/tests/test_mappers.py
tivol/tests/test_migration_handler_base.py
tivol/tests/test_plugins.py
tivol/tests/assets/__init__.py
tivol/tests/assets/entrypoint_for_tests.py
tivol/tests/assets/mappers_for_tests.py
tivol/tests/assets/migration_handlers.py
django_tivol-0.0.1.dist-info/LICENSE
django_tivol-0.0.1.dist-info/METADATA
django_tivol-0.0.1.dist-info/WHEEL
django_tivol-0.0.1.dist-info/top_level.txt
django_tivol-0.0.1.dist-info/RECORD
