Metadata-Version: 2.1
Name: django-tivol
Version: 0.0.1
Summary: Migrating (dummy) content into a Django site
Home-page: https://github.com/RoySegall/tivol
Author: Roy Segall
Author-email: roy@segall.io
License: MIT
Platform: UNKNOWN
Requires-Dist: PyYAML (==5.3)
Requires-Dist: clikit (==0.4.1)
Requires-Dist: requests (==2.22.0)
